{
  "DIFFICULTY_POINTS": {
    "Facile":    10,
    "Moyen":     15,
    "Difficile": 25
  },
  "CATEGORIES": {
    "authz":     { "label": "Authz & Authn", "color": "#a78bfa" },
    "injection": { "label": "Injection",     "color": "#f87171" },
    "misconfig": { "label": "Misconfig",     "color": "#38bdf8" },
    "other":     { "label": "Autre",         "color": "#9ca3af" }
  },
  "CHALLENGES": [
    { "flagId": "IDOR",            "enabled": true,  "name": "Mes données = Tes données",     "difficulty": "Facile",    "category": "authz",     "hint": "Changer un id pour... d'autres données ?" },
    { "flagId": "DATA_EXPOSURE",   "enabled": true,  "name": "Sensitive Data Exposure",       "difficulty": "Facile",    "category": "misconfig", "hint": "Essayez les différents chemins des wordlists" },
    { "flagId": "PATH_TRAVERSAL",  "enabled": true,  "name": "Exploration fichiers",          "difficulty": "Facile",    "category": "misconfig", "hint": "Les chemins mènent parfois plus loin que prévu." },
    { "flagId": "ZERO_RATING",     "enabled": true,  "name": "Review nulle",   "difficulty": "Facile",    "category": "other",     "hint": "Qui contrôle la note donnée ?" },
    { "flagId": "REFLECTED_XSS",   "enabled": true,  "name": "Reflected XSS", "difficulty": "Facile",    "category": "injection", "hint": "La recherche serait-elle un miroir ?" },
    { "flagId": "MASS_ASSIGNMENT", "enabled": true,  "name": "Go admin",       "difficulty": "Moyen",     "category": "authz",     "hint": "Un champ en trop dans l'update de profil ?" },
    { "flagId": "JWT_FORGING",     "enabled": true,  "name": "Go superadmin",  "difficulty": "Moyen",     "category": "authz",     "hint": "Sommes nous sûr de la robustesse du secret JWT? (jwt.io)" },
    { "flagId": "SQLI",            "enabled": true,  "name": "SQL Injection (Login Bypass)",  "difficulty": "Moyen",     "category": "injection", "hint": "Quelle requête SQL pour se connecter ? " },
    { "flagId": "BUSINESS_LOGIC",  "enabled": true,  "name": "1000 crédits",   "difficulty": "Moyen",     "category": "other",     "hint": "Augmenter ses crédits en exploitant les LIMITES du système." },
    { "flagId": "CSRF",            "enabled": false, "name": "CSRF",           "difficulty": "Moyen",     "category": "other",     "hint": "Un script exécuté coté client pour effectuer une action" },
    { "flagId": "SQLI_UNION",      "enabled": true,  "name": "SQL Injection (UNION)",         "difficulty": "Difficile", "category": "injection", "hint": "Voir l'academy et https://github.com/swisskyrepo/PayloadsAllTheThings/blob/master/SQL%20Injection/SQLite%20Injection.md" },
    { "flagId": "STORED_XSS",      "enabled": false, "name": "Stored XSS",     "difficulty": "Difficile", "category": "injection", "hint": "Et si on enregistrait du script dans la BD ?" },
    { "flagId": "SSRF",            "enabled": false, "name": "SSRF",           "difficulty": "Difficile", "category": "injection", "hint": "XXXXX" },
    { "flagId": "COOKIE_THEFT",    "enabled": false, "name": "Vol de cookie",  "difficulty": "Difficile", "category": "injection", "hint": "Un script exécuté coté client peut permettre de lire et exfiltrer un token ;)" }
  ]
}
